grpc_test/__init__.py
grpc_test/helloworld_pb2_grpc.py
grpc_test/py.typed
grpc_test/xyz/__init__.py
grpc_test/xyz/msg_pb2.py
grpc_test/xyz/msg_pb2.pyi
datability_grpc_python_test-0.0.5.dist-info/METADATA
datability_grpc_python_test-0.0.5.dist-info/WHEEL
datability_grpc_python_test-0.0.5.dist-info/top_level.txt
datability_grpc_python_test-0.0.5.dist-info/RECORD
