Metadata-Version: 2.1
Name: datability-grpc-python-test
Version: 0.0.5
Summary: This is a test.
Classifier: Programming Language :: Python :: 3
Classifier: License :: OSI Approved :: MIT License
Classifier: Operating System :: OS Independent
Requires-Python: >=3.8
